pacing_and_leading/__init__.py
pacing_and_leading/arrow.py
pacing_and_leading/composite.py
pacing_and_leading/control.py
pacing_and_leading/cursors.py
pacing_and_leading/display.py
pacing_and_leading/experiment.py
pacing_and_leading/geometry.py
pacing_and_leading/gui.py
pacing_and_leading/hard_targets.py
pacing_and_leading/log.py
pacing_and_leading/mediators.py
pacing_and_leading/similarities.py
pacing_and_leading/soft_targets.py
pacing_and_leading/vertical_targets.py
pacing_and_leading-1.0.data/scripts/pacing_and_leading
pacing_and_leading-1.0.data/scripts/pacing_and_leading_simlog
pacing_and_leading-1.0.dist-info/DESCRIPTION.rst
pacing_and_leading-1.0.dist-info/METADATA
pacing_and_leading-1.0.dist-info/RECORD
pacing_and_leading-1.0.dist-info/WHEEL
pacing_and_leading-1.0.dist-info/metadata.json
pacing_and_leading-1.0.dist-info/top_level.txt
