Metadata-Version: 2.0
Name: pacing-and-leading
Version: 1.0
Summary: pacing and leading experiment
Home-page: UNKNOWN
Author: Vincent Berenz
Author-email: vberenz@tuebingen.mpg.de
License: UNKNOWN
Platform: UNKNOWN
Requires-Dist: matplotlib
Requires-Dist: numpy
